coliseum/__init__.py
coliseum/__main__.py
coliseum/_map.py
coliseum/_metadata.py
coliseum/_version.py
coliseum/debug.py
coliseum/enemies.py
coliseum/player.py
coliseum/tournaments.py
coliseum-1.0.5.dist-info/LICENSE
coliseum-1.0.5.dist-info/METADATA
coliseum-1.0.5.dist-info/WHEEL
coliseum-1.0.5.dist-info/top_level.txt
coliseum-1.0.5.dist-info/RECORD
