Metadata-Version: 2.1
Name: coliseum
Version: 1.0.5
Summary: a simple, turn-based command line game in python
Home-page: https://github.com/signebedi/coliseum
Author: Sig Janoska-Bedi
Author-email: signe@siftingwinnowing.com
License: MIT
Classifier: Programming Language :: Python :: 3
Classifier: License :: OSI Approved :: MIT License
Classifier: Operating System :: OS Independent
Requires-Python: >=3.8
License-File: LICENSE
Requires-Dist: colorama (<1.0.0)
Requires-Dist: pandas (<3.0.0)
Requires-Dist: pytest (<8.0.0)
